[
  {
    "text": "- Who loves cinnamon rolls?",
    "start": 0.92,
    "duration": 2.43
  },
  {
    "text": "Oh my gosh. I love 'em.",
    "start": 3.35,
    "duration": 2.08
  },
  {
    "text": "And when I make 'em with yeast",
    "start": 5.43,
    "duration": 2.02
  },
  {
    "text": "and all that, you know, it takes so long.",
    "start": 7.45,
    "duration": 3.53
  },
  {
    "text": "And I was readin' this little recipe",
    "start": 10.98,
    "duration": 3.09
  },
  {
    "text": "in somebody's magazine.",
    "start": 14.07,
    "duration": 1.68
  },
  {
    "text": "It wasn't mine",
    "start": 15.75,
    "duration": 1.81
  },
  {
    "text": "but it was in a magazine",
    "start": 17.56,
    "duration": 2.68
  },
  {
    "text": "and it was an easy cinnamon roll",
    "start": 20.24,
    "duration": 3.11
  },
  {
    "text": "that you actually cook in the air fryer.",
    "start": 23.35,
    "duration": 2.77
  },
  {
    "text": "So I said, ooh, that's a double winner.",
    "start": 26.12,
    "duration": 2.89
  },
  {
    "text": "So I'm gonna be usin''''' crescent rolls.",
    "start": 29.01,
    "duration": 4.62
  },
  {
    "text": "They recommend crescent rolls.",
    "start": 33.63,
    "duration": 2.0
  },
  {
    "text": "And I'm gonna add 1/3\nof a cup of brown sugar",
    "start": 35.63,
    "duration": 3.74
  },
  {
    "text": "and about 1/2 a teaspoon of cinnamon",
    "start": 40.75,
    "duration": 3.87
  },
  {
    "text": "and about 1/3 of a cup of powdered sugar.",
    "start": 49.29,
    "duration": 4.723
  },
  {
    "text": "And I'm gonna mix this together",
    "start": 64.176,
    "duration": 1.244
  },
  {
    "text": "with 2 tablespoons of melted butter.",
    "start": 65.42,
    "duration": 4.023
  },
  {
    "text": "So this is gonna make our crescent rolls.",
    "start": 71.83,
    "duration": 3.04
  },
  {
    "text": "It's gonna turn our crescent rolls",
    "start": 74.87,
    "duration": 1.47
  },
  {
    "text": "into cinnamon rolls.",
    "start": 76.34,
    "duration": 2.643
  },
  {
    "text": "I adore a cinnamon roll",
    "start": 80.98,
    "duration": 2.05
  },
  {
    "text": "with all that ooey gooey icing on top.",
    "start": 84.2,
    "duration": 3.333
  },
  {
    "text": "You know, when Eddie and I was",
    "start": 88.83,
    "duration": 1.61
  },
  {
    "text": "out there flyin' a lot before COVID",
    "start": 90.44,
    "duration": 1.94
  },
  {
    "text": "oh my gosh, we'd be in the airports.",
    "start": 93.275,
    "duration": 5.0
  },
  {
    "text": "And those, you know what\ncinnamon rolls I'm talkin' about.",
    "start": 99.49,
    "duration": 2.96
  },
  {
    "text": "You could get extra goop on top.",
    "start": 102.45,
    "duration": 3.11
  },
  {
    "text": "Oh my goodness.",
    "start": 105.56,
    "duration": 1.05
  },
  {
    "text": "It was so hard for me to walk by those",
    "start": 106.61,
    "duration": 3.1
  },
  {
    "text": "and not get one.",
    "start": 109.71,
    "duration": 4.13
  },
  {
    "text": "But I didn't get 'em, did I Eddie?",
    "start": 113.84,
    "duration": 1.666
  },
  {
    "text": "- [Eddie] No",
    "start": 115.506,
    "duration": 1.11
  },
  {
    "text": "- Maybe once.",
    "start": 116.616,
    "duration": 1.717
  },
  {
    "text": "- [Eddie] Maybe you did. (laughing)",
    "start": 118.333,
    "duration": 2.067
  },
  {
    "text": "- Maybe once but you know,",
    "start": 120.4,
    "duration": 2.12
  },
  {
    "text": "I could've got one every\ntime I walked by one",
    "start": 122.52,
    "duration": 2.93
  },
  {
    "text": "but I didn't.",
    "start": 125.45,
    "duration": 1.007
  },
  {
    "text": "But not 'cause I didn't want it.",
    "start": 127.61,
    "duration": 1.74
  },
  {
    "text": "- [Eddie] Well I know in Minneapolis",
    "start": 129.35,
    "duration": 2.31
  },
  {
    "text": "depending on which-",
    "start": 131.66,
    "duration": 1.247
  },
  {
    "text": "- Yes.",
    "start": 132.907,
    "duration": 0.833
  },
  {
    "text": "- [Eddie] Terminal we were in.",
    "start": 133.74,
    "duration": 1.27
  },
  {
    "text": "- We were in.",
    "start": 135.01,
    "duration": 0.833
  },
  {
    "text": "- [Eddie] There was one\nthat was worth going to",
    "start": 135.843,
    "duration": 2.767
  },
  {
    "text": "though because it had that bakery in it.",
    "start": 138.61,
    "duration": 3.08
  },
  {
    "text": "And they had the best\ncinnamon rolls there.",
    "start": 141.69,
    "duration": 3.4
  },
  {
    "text": "- Oh gosh, that's what we miss\nabout Minnesota, isn't it.",
    "start": 145.09,
    "duration": 5.0
  },
  {
    "text": "All right. Let's see.",
    "start": 151.46,
    "duration": 0.833
  },
  {
    "text": "I want to make sure I get this right.",
    "start": 152.293,
    "duration": 2.137
  },
  {
    "text": "So combined butter, brown\nsugar, cinnamon, and salt.",
    "start": 154.43,
    "duration": 4.51
  },
  {
    "text": "And it just calls up an\n1/8 of a teaspoon of salt.",
    "start": 158.94,
    "duration": 3.81
  },
  {
    "text": "So that would probably be an eighth.",
    "start": 162.75,
    "duration": 3.713
  },
  {
    "text": "And now it said spread\nbutter mixture over dough,",
    "start": 167.56,
    "duration": 5.0
  },
  {
    "text": "leaving a fourth of an inch border.",
    "start": 172.57,
    "duration": 2.653
  },
  {
    "text": "Alright, now let's see what we do",
    "start": 177.26,
    "duration": 1.74
  },
  {
    "text": "with the cream cheese, okay.",
    "start": 179.0,
    "duration": 2.67
  },
  {
    "text": "Calls for cream cheese, but\nthat goes in that yummy icing.",
    "start": 181.67,
    "duration": 3.953
  },
  {
    "text": "All right. So we got that mixed up good.",
    "start": 186.61,
    "duration": 2.48
  },
  {
    "text": "So I'm going to open my Crescent Rolls.",
    "start": 189.09,
    "duration": 2.313
  },
  {
    "text": "This thing always scares\nme, if it pops before",
    "start": 194.258,
    "duration": 2.802
  },
  {
    "text": "I mean for it to pop.",
    "start": 197.06,
    "duration": 3.703
  },
  {
    "text": "Great dime a day, I don't\nthink they wanted me",
    "start": 206.64,
    "duration": 1.36
  },
  {
    "text": "to get into this.",
    "start": 208.0,
    "duration": 1.533
  },
  {
    "text": "Okay.",
    "start": 210.79,
    "duration": 0.833
  },
  {
    "text": "So we're gonna to unwrap\nthe rolls and you can see",
    "start": 213.18,
    "duration": 5.0
  },
  {
    "text": "I put a little flour\ndown so they won't stick",
    "start": 218.56,
    "duration": 4.98
  },
  {
    "text": "And I may need a little bit more flour,",
    "start": 223.54,
    "duration": 2.633
  },
  {
    "text": "'cause I don't want\nthese puppies stickin'.",
    "start": 228.6,
    "duration": 2.397
  },
  {
    "text": "So we want to just press these together",
    "start": 233.16,
    "duration": 4.69
  },
  {
    "text": "So it'll make one long piece of dough.",
    "start": 241.77,
    "duration": 3.733
  },
  {
    "text": "All right. Now it said spread\nbutter mixture over dough.",
    "start": 248.34,
    "duration": 5.0
  },
  {
    "text": "All right. No let's back up.",
    "start": 254.66,
    "duration": 2.21
  },
  {
    "text": "Roll out Crescent dough in one piece,",
    "start": 256.87,
    "duration": 1.95
  },
  {
    "text": "pinch seams together and fold in half.",
    "start": 258.82,
    "duration": 2.28
  },
  {
    "text": "Okay. So we will fold that in half.",
    "start": 262.77,
    "duration": 4.31
  },
  {
    "text": "And we'll pinch it back together again.",
    "start": 275.097,
    "duration": 2.526
  },
  {
    "text": "Now after I pick up\nwhat their putting down,",
    "start": 279.79,
    "duration": 4.49
  },
  {
    "text": "what that recipe is putting down.",
    "start": 284.28,
    "duration": 1.87
  },
  {
    "text": "I may be changing this\na little bit. In fact,",
    "start": 286.15,
    "duration": 2.85
  },
  {
    "text": "I am going to change some of it already.",
    "start": 289.0,
    "duration": 2.743
  },
  {
    "text": "All right.",
    "start": 292.81,
    "duration": 0.833
  },
  {
    "text": "And then what does it say to do?",
    "start": 293.643,
    "duration": 1.177
  },
  {
    "text": "Pinch seams together and fold in half,",
    "start": 294.82,
    "duration": 1.65
  },
  {
    "text": "roll dough into a nine by seven rectangle.",
    "start": 296.47,
    "duration": 4.063
  },
  {
    "text": "Okay. So I'm going to\nhave to find my little,",
    "start": 301.4,
    "duration": 2.947
  },
  {
    "text": "my little rolling pin.",
    "start": 304.347,
    "duration": 2.186
  },
  {
    "text": "Here's my little handy dandy rolling pin.",
    "start": 308.59,
    "duration": 2.083
  },
  {
    "text": "It's trying to stick together, isn't it?",
    "start": 323.52,
    "duration": 2.003
  },
  {
    "text": "Now their recipe, I think\ncalled for just a regular,",
    "start": 331.06,
    "duration": 3.513
  },
  {
    "text": "an eight ounce tube of Crescent rolls.",
    "start": 336.08,
    "duration": 5.0
  },
  {
    "text": "And I don't know what we'll\nuse, but we're using the jumbo,",
    "start": 343.01,
    "duration": 4.993
  },
  {
    "text": "'cause if I make cinnamon rolls",
    "start": 349.535,
    "duration": 2.45
  },
  {
    "text": "I want to have as many as i'm\ncapable of making at one time.",
    "start": 351.985,
    "duration": 5.0
  },
  {
    "text": "Okay. Does that look like what they say?",
    "start": 361.35,
    "duration": 3.11
  },
  {
    "text": "A nine to seven, Eddie?",
    "start": 364.46,
    "duration": 1.353
  },
  {
    "text": "- [Eddie] You've got your\nlittle handy measuring tool",
    "start": 370.84,
    "duration": 2.06
  },
  {
    "text": "on the side there.",
    "start": 372.9,
    "duration": 0.84
  },
  {
    "text": "- Oh yeah.",
    "start": 373.74,
    "duration": 1.216
  },
  {
    "text": "(laughing)",
    "start": 374.956,
    "duration": 0.833
  },
  {
    "text": "Alright.",
    "start": 375.789,
    "duration": 0.833
  },
  {
    "text": "I know, you know,",
    "start": 378.37,
    "duration": 0.833
  },
  {
    "text": "this is my favorite\ncuttin' board and it's,",
    "start": 379.203,
    "duration": 4.617
  },
  {
    "text": "it's a Paula Dean cuttin' board",
    "start": 383.82,
    "duration": 1.96
  },
  {
    "text": "Meyer made this for me",
    "start": 387.51,
    "duration": 3.05
  },
  {
    "text": "years ago and it's got your pie circle,",
    "start": 390.56,
    "duration": 3.23
  },
  {
    "text": "so you can figure out how,",
    "start": 393.79,
    "duration": 1.952
  },
  {
    "text": "what size to make roll\nout your pie crust to.",
    "start": 395.742,
    "duration": 3.958
  },
  {
    "text": "Okay, so it said a nine by seven.",
    "start": 399.7,
    "duration": 3.493
  },
  {
    "text": "Well, I can't, I can't,",
    "start": 407.1,
    "duration": 1.223
  },
  {
    "text": "I don't know if I'll be\nable to move it Eddie.",
    "start": 410.27,
    "duration": 2.3
  },
  {
    "text": "- [Eddie] That looks about right.",
    "start": 413.73,
    "duration": 1.46
  },
  {
    "text": "- Yeah.",
    "start": 415.19,
    "duration": 0.833
  },
  {
    "text": "Like I say we've actually got more dough",
    "start": 416.96,
    "duration": 2.26
  },
  {
    "text": "than their recipe had.",
    "start": 420.86,
    "duration": 3.743
  },
  {
    "text": "All right, so now we are\ngonna spread our cinnamon",
    "start": 425.77,
    "duration": 4.327
  },
  {
    "text": "And sugar mixture,",
    "start": 438.16,
    "duration": 1.423
  },
  {
    "text": "and we're gonna leave about\na half an inch border.",
    "start": 440.64,
    "duration": 3.443
  },
  {
    "text": "I may need some more cinnamon and",
    "start": 449.09,
    "duration": 3.213
  },
  {
    "text": "butter and sugar since we got more dough.",
    "start": 456.317,
    "duration": 2.753
  },
  {
    "text": "I don't want no skimpy cinnamon roll.",
    "start": 465.883,
    "duration": 2.83
  },
  {
    "text": "That'd be just enough\nto make your mouth mad.",
    "start": 471.75,
    "duration": 2.303
  },
  {
    "text": "Okay. Now here's where I'm\ngoing to be a little different",
    "start": 483.18,
    "duration": 4.44
  },
  {
    "text": "from their recipe.",
    "start": 489.75,
    "duration": 1.563
  },
  {
    "text": "To me, a cinnamon roll\nis not a cinnamon roll,",
    "start": 494.21,
    "duration": 2.883
  },
  {
    "text": "unless it has nuts and raisins.",
    "start": 498.49,
    "duration": 2.203
  },
  {
    "text": "So I am gonna to be adding that.",
    "start": 501.95,
    "duration": 5.0
  },
  {
    "text": "Yeah, could of stood a\nlittle bit more sugar.",
    "start": 508.51,
    "duration": 1.83
  },
  {
    "text": "Couldn't I, Eddie?",
    "start": 510.34,
    "duration": 1.123
  },
  {
    "text": "Maybe that would be enough.\nThey say leave how much?",
    "start": 513.363,
    "duration": 2.6
  },
  {
    "text": "A fourth of an inch.",
    "start": 517.57,
    "duration": 1.02
  },
  {
    "text": "So I've left more than\na fourth of an inch.",
    "start": 518.59,
    "duration": 2.613
  },
  {
    "text": "So lets bring that out a little bit more.",
    "start": 522.91,
    "duration": 3.543
  },
  {
    "text": "You know, if this turns out good,",
    "start": 530.32,
    "duration": 2.123
  },
  {
    "text": "what an easy way to satisfy\na cinnamon roll cravin'.",
    "start": 533.36,
    "duration": 5.0
  },
  {
    "text": "'Cause once I know what I'm doing,",
    "start": 541.537,
    "duration": 1.873
  },
  {
    "text": "this is going to be really, really easy.",
    "start": 543.41,
    "duration": 2.553
  },
  {
    "text": "Okay. Now I've got to go stop",
    "start": 549.06,
    "duration": 3.26
  },
  {
    "text": "and find my nuts",
    "start": 552.32,
    "duration": 2.55
  },
  {
    "text": "and my raisins.",
    "start": 554.87,
    "duration": 2.13
  },
  {
    "text": "This is the beauty of cooking, y'all.",
    "start": 557.0,
    "duration": 3.238
  },
  {
    "text": "You have the ability to make it",
    "start": 560.238,
    "duration": 4.305
  },
  {
    "text": "any way you want it.",
    "start": 564.543,
    "duration": 1.667
  },
  {
    "text": "Express yourself.",
    "start": 569.05,
    "duration": 1.293
  },
  {
    "text": "Does that look like enough nuts, Eddie?",
    "start": 574.31,
    "duration": 1.95
  },
  {
    "text": "- [Eddie] Yeah that looks good.",
    "start": 577.471,
    "duration": 0.833
  },
  {
    "text": "- I don't want to be\nshy of no nuts either.",
    "start": 578.304,
    "duration": 2.689
  },
  {
    "text": "All right here come these\nwonderful raisins that just add a",
    "start": 582.92,
    "duration": 3.12
  },
  {
    "text": "little bit more sweetness to it.",
    "start": 586.04,
    "duration": 2.043
  },
  {
    "text": "I love raisins.",
    "start": 590.23,
    "duration": 1.16
  },
  {
    "text": "I love raisins in my oatmeal\ncookies and in my cinnamon",
    "start": 591.39,
    "duration": 4.97
  },
  {
    "text": "rolls.",
    "start": 596.36,
    "duration": 1.083
  },
  {
    "text": "So, I tell y'all make it,",
    "start": 602.01,
    "duration": 2.52
  },
  {
    "text": "make it the way the recipe\nhas been given the first time.",
    "start": 604.53,
    "duration": 2.74
  },
  {
    "text": "But you know,",
    "start": 607.27,
    "duration": 1.04
  },
  {
    "text": "I've just been in the\nkitchen long enough to know",
    "start": 608.31,
    "duration": 2.45
  },
  {
    "text": "that I like nuts and raisins.",
    "start": 612.82,
    "duration": 4.773
  },
  {
    "text": "So here we go.",
    "start": 620.14,
    "duration": 0.833
  },
  {
    "text": "It said to start at the long,",
    "start": 620.973,
    "duration": 3.906
  },
  {
    "text": "at the long side, roll up dough,",
    "start": 624.879,
    "duration": 2.734
  },
  {
    "text": "like a jelly roll.",
    "start": 630.559,
    "duration": 1.124
  },
  {
    "text": "Okay.",
    "start": 636.904,
    "duration": 0.833
  },
  {
    "text": "Ooo this is going to be good.",
    "start": 641.313,
    "duration": 5.0
  },
  {
    "text": "This is the way,",
    "start": 650.253,
    "duration": 1.37
  },
  {
    "text": "I'm going to dampen that seam",
    "start": 655.1,
    "duration": 1.65
  },
  {
    "text": "just a little bit to",
    "start": 656.75,
    "duration": 1.55
  },
  {
    "text": "see if I can get it to seal",
    "start": 661.922,
    "duration": 1.628
  },
  {
    "text": "a little bit better.",
    "start": 665.5,
    "duration": 1.183
  },
  {
    "text": "Yeah.",
    "start": 691.44,
    "duration": 0.833
  },
  {
    "text": "Yes, yes, yes.",
    "start": 694.855,
    "duration": 2.338
  },
  {
    "text": "I'm trying to bring all my\nfillin' all the way to the end.",
    "start": 700.81,
    "duration": 4.88
  },
  {
    "text": "I think we gonna have a good,",
    "start": 711.98,
    "duration": 1.733
  },
  {
    "text": "right good cinnamon roll y'all.",
    "start": 714.65,
    "duration": 2.123
  },
  {
    "text": "All right. Now let's see if they,",
    "start": 722.87,
    "duration": 1.993
  },
  {
    "text": "let's see if they recommend\nbrushing it with an egg.",
    "start": 727.34,
    "duration": 2.6
  },
  {
    "text": "No, they don't recommend\nputtin' it with an egg.",
    "start": 739.12,
    "duration": 3.457
  },
  {
    "text": "I mean, coatin' it with an egg.",
    "start": 744.213,
    "duration": 3.214
  },
  {
    "text": "Ok. So they just tell us to cut,",
    "start": 747.427,
    "duration": 2.366
  },
  {
    "text": "and make six",
    "start": 752.954,
    "duration": 0.976
  },
  {
    "text": "cinnamon rolls.",
    "start": 753.93,
    "duration": 1.35
  },
  {
    "text": "But I think we're gonna\nget more than that because",
    "start": 755.28,
    "duration": 5.0
  },
  {
    "text": "we used the larger Crescent dough.",
    "start": 763.56,
    "duration": 2.043
  },
  {
    "text": "You do want to make sure that\nyou cut them all about the",
    "start": 778.747,
    "duration": 2.723
  },
  {
    "text": "same size though.",
    "start": 781.47,
    "duration": 1.073
  },
  {
    "text": "(Timer dings)",
    "start": 783.771,
    "duration": 1.389
  },
  {
    "text": "Ooo, that tells me something is ready.",
    "start": 785.16,
    "duration": 3.553
  },
  {
    "text": "Okay.",
    "start": 798.722,
    "duration": 0.833
  },
  {
    "text": "Look at these. Y'all I got to\ncheck something in the oven.",
    "start": 801.99,
    "duration": 4.54
  },
  {
    "text": "Y'all talk amongst yourselves.",
    "start": 806.53,
    "duration": 2.23
  },
  {
    "text": "And I think these are going\nto probably cook beautifully",
    "start": 811.648,
    "duration": 2.942
  },
  {
    "text": "y'all because you know how\ngood my biscuits bake in this.",
    "start": 814.59,
    "duration": 5.0
  },
  {
    "text": "The biscuits are wonderful.",
    "start": 822.377,
    "duration": 1.886
  },
  {
    "text": "Ooh, I'm so excited.",
    "start": 829.2,
    "duration": 2.653
  },
  {
    "text": "A cinnamon roll in like 10 or 15 minutes.",
    "start": 833.23,
    "duration": 3.423
  },
  {
    "text": "Yay.",
    "start": 838.86,
    "duration": 0.833
  },
  {
    "text": "I could have rolled them\na little bit tighter, but,",
    "start": 847.77,
    "duration": 2.73
  },
  {
    "text": "But I didn't have 'em\nin the right position.",
    "start": 861.4,
    "duration": 2.713
  },
  {
    "text": "You know, when I started rolling up,",
    "start": 865.49,
    "duration": 1.52
  },
  {
    "text": "I should have turned it towards me",
    "start": 867.01,
    "duration": 1.96
  },
  {
    "text": "and I would have had a\ntighter, tighter roll.",
    "start": 871.22,
    "duration": 5.0
  },
  {
    "text": "All right.",
    "start": 876.51,
    "duration": 0.833
  },
  {
    "text": "I'm gonna give those a spray,",
    "start": 883.327,
    "duration": 2.417
  },
  {
    "text": "And I'ma put them in our air fryer at 350,",
    "start": 886.63,
    "duration": 3.627
  },
  {
    "text": "for 10 minutes.",
    "start": 898.62,
    "duration": 1.25
  },
  {
    "text": "And I'll be checking those\nbecause I don't know what kind of",
    "start": 901.89,
    "duration": 2.89
  },
  {
    "text": "air fryer they were usin''''''',",
    "start": 904.78,
    "duration": 1.207
  },
  {
    "text": "but I know it wasn't a Paula Dean,",
    "start": 905.987,
    "duration": 1.883
  },
  {
    "text": "it was a kind of a small air fryer.",
    "start": 907.87,
    "duration": 3.54
  },
  {
    "text": "So I'm gonna keep my eye on that.",
    "start": 911.41,
    "duration": 4.123
  },
  {
    "text": "But while they're baking,",
    "start": 918.3,
    "duration": 2.02
  },
  {
    "text": "I've got to make our top\nto go on these hot cinnamon",
    "start": 920.32,
    "duration": 5.0
  },
  {
    "text": "rolls. Because to me it's the best part.",
    "start": 926.377,
    "duration": 3.206
  },
  {
    "text": "This is my first check y'all",
    "start": 931.57,
    "duration": 1.94
  },
  {
    "text": "and they are looking good,",
    "start": 935.58,
    "duration": 2.423
  },
  {
    "text": "but I'm going to cook them. You see I've,",
    "start": 940.01,
    "duration": 2.15
  },
  {
    "text": "I'll cook in my air fryer.\nI'll usually cook on like 400,",
    "start": 942.16,
    "duration": 4.093
  },
  {
    "text": "but this recipe called for 350.",
    "start": 947.36,
    "duration": 2.58
  },
  {
    "text": "So I'm bumping it up to 375.",
    "start": 949.94,
    "duration": 4.3
  },
  {
    "text": "And I'm addin' another five minutes.",
    "start": 954.24,
    "duration": 2.73
  },
  {
    "text": "So in your air fryer,",
    "start": 956.97,
    "duration": 1.54
  },
  {
    "text": "if you have an air fryer or\nyou putting this in a regular",
    "start": 958.51,
    "duration": 4.417
  },
  {
    "text": "oven, you'll just have\nto play with that time",
    "start": 962.927,
    "duration": 4.133
  },
  {
    "text": "until you get it right.",
    "start": 968.56,
    "duration": 1.93
  },
  {
    "text": "Okay. So y'all saw what the cinnamon rolls",
    "start": 970.49,
    "duration": 4.23
  },
  {
    "text": "looked like after 10 minutes,",
    "start": 974.72,
    "duration": 1.943
  },
  {
    "text": "because I usually cook\non like 400 degrees,",
    "start": 978.102,
    "duration": 3.408
  },
  {
    "text": "but I'm doing what the recipe\nsaid and starting at 350,",
    "start": 981.51,
    "duration": 3.243
  },
  {
    "text": "but I did bump it up to 375\nand I added another five",
    "start": 985.76,
    "duration": 3.85
  },
  {
    "text": "minutes.",
    "start": 989.61,
    "duration": 1.21
  },
  {
    "text": "All right. So I'm going\nto make that delicious,",
    "start": 990.82,
    "duration": 2.813
  },
  {
    "text": "gooey topping that we love\nso much on cinnamon rolls.",
    "start": 995.81,
    "duration": 5.0
  },
  {
    "text": "Now the recipe calls for two\ntablespoons of half and half,",
    "start": 1001.03,
    "duration": 3.94
  },
  {
    "text": "four ounces of cream cheese,\ndid it call for four ounces or",
    "start": 1004.97,
    "duration": 3.11
  },
  {
    "text": "three ounces?",
    "start": 1008.08,
    "duration": 0.833
  },
  {
    "text": "- [Theresa] Three ounces.",
    "start": 1008.913,
    "duration": 0.833
  },
  {
    "text": "- I added a good 'nother ounce",
    "start": 1009.746,
    "duration": 1.964
  },
  {
    "text": "because the recipe said it made",
    "start": 1011.71,
    "duration": 3.16
  },
  {
    "text": "six cinnamon rolls while mine may,",
    "start": 1014.87,
    "duration": 2.71
  },
  {
    "text": "because I was using the Grands, mine made",
    "start": 1017.58,
    "duration": 4.35
  },
  {
    "text": "2, 4, 6, 8, 10.",
    "start": 1023.476,
    "duration": 2.837
  },
  {
    "text": "So I might need a little\nbit more of the icing.",
    "start": 1027.8,
    "duration": 5.0
  },
  {
    "text": "So it called for a third\nof a cup of powdered sugar.",
    "start": 1033.32,
    "duration": 2.5
  },
  {
    "text": "Well, I'm doin' a heaping cup.",
    "start": 1035.82,
    "duration": 2.247
  },
  {
    "text": "And I'm just (hand mixer motor sounds)",
    "start": 1042.55,
    "duration": 4.15
  },
  {
    "text": "All right, I'm gonna to\nget a little vanilla.",
    "start": 1046.7,
    "duration": 2.6
  },
  {
    "text": "I don't know if it asks for vanilla but",
    "start": 1049.3,
    "duration": 3.29
  },
  {
    "text": "I'm coming out with my own vanilla spices",
    "start": 1056.256,
    "duration": 5.0
  },
  {
    "text": "And I can't wait to\nshare these with y'all.",
    "start": 1064.01,
    "duration": 3.33
  },
  {
    "text": "So this is vanilla paste.",
    "start": 1067.34,
    "duration": 2.383
  },
  {
    "text": "So I'm going to add just a little bit.",
    "start": 1070.64,
    "duration": 2.03
  },
  {
    "text": "You can see the paste is a\nlittle thicker than vanilla,",
    "start": 1072.67,
    "duration": 4.18
  },
  {
    "text": "the regular vanilla flavoring.",
    "start": 1078.06,
    "duration": 1.723
  },
  {
    "text": "(Hand mixer motor sounds)",
    "start": 1081.944,
    "duration": 2.296
  },
  {
    "text": "Wow.",
    "start": 1084.24,
    "duration": 1.013
  },
  {
    "text": "Ooh.",
    "start": 1087.37,
    "duration": 1.113
  },
  {
    "text": "Look at these. Now, so in\nour air fryer cooking it 350",
    "start": 1092.71,
    "duration": 5.0
  },
  {
    "text": "degrees, these took 15 minutes,",
    "start": 1100.87,
    "duration": 5.0
  },
  {
    "text": "but had I been cooking them on 400 or 375?",
    "start": 1108.62,
    "duration": 4.41
  },
  {
    "text": "They might've gotten\ndone in three minutes.",
    "start": 1113.03,
    "duration": 4.535
  },
  {
    "text": "Ten minutes.",
    "start": 1117.565,
    "duration": 1.505
  },
  {
    "text": "All right. So Theresa,\nI'm so excited about",
    "start": 1119.07,
    "duration": 2.45
  },
  {
    "text": "these I can't think.",
    "start": 1121.52,
    "duration": 1.133
  },
  {
    "text": "I can't think, do we have\na platter or something?",
    "start": 1123.858,
    "duration": 1.202
  },
  {
    "text": "I can take these out and put them on.",
    "start": 1125.06,
    "duration": 1.46
  },
  {
    "text": "- [Eddie] Yeah, right here on the",
    "start": 1126.52,
    "duration": 1.65
  },
  {
    "text": "(tongs clacking)",
    "start": 1129.568,
    "duration": 1.849
  },
  {
    "text": "- Oh, yay.",
    "start": 1131.417,
    "duration": 0.995
  },
  {
    "text": "- [Theresa] I was gonna\nsay \"You're asking me?\"",
    "start": 1132.412,
    "duration": 1.038
  },
  {
    "text": "I don't know where everything is yet.",
    "start": 1133.45,
    "duration": 3.083
  },
  {
    "text": "- Eddie moved this piece\ninto the kitchen y'all.",
    "start": 1138.44,
    "duration": 4.72
  },
  {
    "text": "This was actually in the\nlaundry room at River Bend",
    "start": 1143.16,
    "duration": 3.12
  },
  {
    "text": "for us to fold clothes on.",
    "start": 1147.56,
    "duration": 1.633
  },
  {
    "text": "And so Eddie said you just\nneed something else down here,",
    "start": 1150.46,
    "duration": 4.45
  },
  {
    "text": "so he put it in here and now I am,",
    "start": 1154.91,
    "duration": 4.42
  },
  {
    "text": "what is going on?",
    "start": 1160.59,
    "duration": 1.62
  },
  {
    "text": "And now I am so dependent on it.",
    "start": 1162.21,
    "duration": 2.693
  },
  {
    "text": "It's got to stay there forever Eddie.",
    "start": 1166.4,
    "duration": 2.343
  },
  {
    "text": "All right. So I'm going to take these out,",
    "start": 1171.05,
    "duration": 2.563
  },
  {
    "text": "put 'em on our platter.",
    "start": 1175.31,
    "duration": 1.493
  },
  {
    "text": "They look delicious.",
    "start": 1178.84,
    "duration": 1.733
  },
  {
    "text": "And remember I always recommend sprayin'.",
    "start": 1182.77,
    "duration": 2.987
  },
  {
    "text": "Your biscuits or any kind\nof dough that you're making.",
    "start": 1188.94,
    "duration": 2.983
  },
  {
    "text": "All right.",
    "start": 1194.86,
    "duration": 0.833
  },
  {
    "text": "All right. Those in the front,",
    "start": 1200.73,
    "duration": 1.19
  },
  {
    "text": "I have found that in an air fryer,",
    "start": 1201.92,
    "duration": 4.68
  },
  {
    "text": "the food in the back\ntends to cook not as fast.",
    "start": 1206.6,
    "duration": 5.0
  },
  {
    "text": "(background talking)",
    "start": 1212.641,
    "duration": 1.586
  },
  {
    "text": "So i'm going to take these",
    "start": 1214.227,
    "duration": 1.3
  },
  {
    "text": "and put them back in\njust for a few minutes.",
    "start": 1216.878,
    "duration": 3.585
  },
  {
    "text": "Hey, you got it.",
    "start": 1225.27,
    "duration": 0.833
  },
  {
    "text": "All right.",
    "start": 1227.78,
    "duration": 1.163
  },
  {
    "text": "Here we go, the best part.",
    "start": 1232.97,
    "duration": 1.773
  },
  {
    "text": "- [Theresa] Those are really pretty.",
    "start": 1237.747,
    "duration": 1.193
  },
  {
    "text": "- Aren't they pretty?",
    "start": 1238.94,
    "duration": 1.423
  },
  {
    "text": "I'm just amazed that we can\nhave a cinnamon rolls so quick.",
    "start": 1243.33,
    "duration": 5.0
  },
  {
    "text": "Alright.",
    "start": 1250.62,
    "duration": 0.833
  },
  {
    "text": "Y'all want half or whole?",
    "start": 1252.72,
    "duration": 1.25
  },
  {
    "text": "- [Theresa] I want half.",
    "start": 1254.937,
    "duration": 1.842
  },
  {
    "text": "- Okay, any particular one?",
    "start": 1256.779,
    "duration": 2.181
  },
  {
    "text": "- [Theresa] Nope.",
    "start": 1258.96,
    "duration": 1.579
  },
  {
    "text": "(laughing)",
    "start": 1260.539,
    "duration": 2.25
  },
  {
    "text": "- Eddie, you want half or whole.",
    "start": 1264.57,
    "duration": 2.76
  },
  {
    "text": "- [Theresa] You know you want",
    "start": 1267.33,
    "duration": 1.55
  },
  {
    "text": "- Well Eddie's kinda been\nwatching what he eats",
    "start": 1268.88,
    "duration": 2.33
  },
  {
    "text": "- [Theresa] He's, I know.",
    "start": 1271.21,
    "duration": 1.044
  },
  {
    "text": "- Cause I've been watching\nhim. What he eats.",
    "start": 1272.254,
    "duration": 2.329
  },
  {
    "text": "- [Theresa] These are good.",
    "start": 1282.523,
    "duration": 2.2
  },
  {
    "text": "- Ain't nothing wrong with a quickie",
    "start": 1284.723,
    "duration": 1.527
  },
  {
    "text": "every now and again y'all.",
    "start": 1286.25,
    "duration": 1.453
  },
  {
    "text": "And that's pretty good for a quickie.",
    "start": 1290.64,
    "duration": 1.98
  },
  {
    "text": "Isn't that yummy?",
    "start": 1295.52,
    "duration": 1.255
  },
  {
    "text": "- [Theresa] Uh huh.",
    "start": 1296.775,
    "duration": 1.661
  },
  {
    "text": "- It's about as good as those\nthat you buy at the airport.",
    "start": 1298.436,
    "duration": 2.78
  },
  {
    "text": "(Eddie laughing)",
    "start": 1301.216,
    "duration": 2.75
  },
  {
    "text": "Nasty Michael, they got boogers.",
    "start": 1304.803,
    "duration": 2.88
  },
  {
    "text": "They got boogers in 'em.",
    "start": 1309.4,
    "duration": 1.703
  },
  {
    "text": "Michael?",
    "start": 1314.819,
    "duration": 0.833
  },
  {
    "text": "- [Michael] What?",
    "start": 1316.568,
    "duration": 0.858
  },
  {
    "text": "- Turn around, look at us.",
    "start": 1317.426,
    "duration": 2.082
  },
  {
    "text": "(laughing)",
    "start": 1319.508,
    "duration": 2.742
  },
  {
    "text": "- [Theresa] You've got\nstuff all over your face.",
    "start": 1322.25,
    "duration": 1.928
  },
  {
    "text": "- Do I? Well, that's\nwhat makes it so good.",
    "start": 1324.178,
    "duration": 2.905
  },
  {
    "text": "So I'm so glad I saw this recipe.",
    "start": 1329.75,
    "duration": 2.713
  },
  {
    "text": "- [Theresa] You made it your own.",
    "start": 1334.09,
    "duration": 1.61
  },
  {
    "text": "- Uh huh, yum.",
    "start": 1335.7,
    "duration": 3.93
  },
  {
    "text": "So next time and there\nwill be a next time.",
    "start": 1339.63,
    "duration": 4.233
  },
  {
    "text": "The next time I would need to\nmake these with no nuts and no",
    "start": 1344.81,
    "duration": 4.55
  },
  {
    "text": "raisins, so our little\ntoddlers can have one.",
    "start": 1349.36,
    "duration": 2.92
  },
  {
    "text": "I didn't think about that.",
    "start": 1352.28,
    "duration": 1.67
  },
  {
    "text": "I was just thinking\nabout big old fat Guinea.",
    "start": 1353.95,
    "duration": 2.553
  },
  {
    "text": "So do try this. It's worth it.",
    "start": 1359.4,
    "duration": 2.623
  },
  {
    "text": "Y'all Max is back in a diaper.",
    "start": 1363.53,
    "duration": 3.05
  },
  {
    "text": "He's up, he's back to his evil ways.",
    "start": 1366.58,
    "duration": 4.62
  },
  {
    "text": "He's pee peein', where\nPumpkin, the cat is been.",
    "start": 1371.2,
    "duration": 3.103
  },
  {
    "text": "So when he comes in here, he\nhas to have on his diaper.",
    "start": 1375.83,
    "duration": 4.183
  },
  {
    "text": "And I just had me a treat.",
    "start": 1381.75,
    "duration": 2.369
  },
  {
    "text": "I had the most wonderful cinnamon roll.",
    "start": 1384.119,
    "duration": 2.884
  },
  {
    "text": "(multiple people talking)",
    "start": 1388.083,
    "duration": 2.036
  },
  {
    "text": "Do you want that treat? Do you\nwant that treat little girl?",
    "start": 1390.119,
    "duration": 3.461
  },
  {
    "text": "You want it bad?",
    "start": 1393.58,
    "duration": 1.87
  },
  {
    "text": "You want it bad?",
    "start": 1395.45,
    "duration": 1.77
  },
  {
    "text": "Say I want it so bad I\ncan hardly turn over.",
    "start": 1397.22,
    "duration": 2.821
  },
  {
    "text": "(laughing)",
    "start": 1400.041,
    "duration": 1.069
  },
  {
    "text": "All right, everybody sit.",
    "start": 1401.11,
    "duration": 1.25
  },
  {
    "text": "- [Eddie] Max, sit.",
    "start": 1405.36,
    "duration": 1.177
  },
  {
    "text": "- You know I can't get\ninto these bags anymore.",
    "start": 1406.537,
    "duration": 2.353
  },
  {
    "text": "They make it so hard to get in 'em.",
    "start": 1408.89,
    "duration": 2.497
  },
  {
    "text": "Okay. Y'all just be patient.",
    "start": 1416.26,
    "duration": 3.76
  },
  {
    "text": "Be patient. My lil childrens.",
    "start": 1420.02,
    "duration": 2.003
  },
  {
    "text": "Can't do it. Can't do it.",
    "start": 1424.402,
    "duration": 1.081
  },
  {
    "text": "All right here. We'll try it this way.",
    "start": 1426.8,
    "duration": 2.473
  },
  {
    "text": "I'm gonna be over the,",
    "start": 1430.227,
    "duration": 1.433
  },
  {
    "text": "I got it!",
    "start": 1431.66,
    "duration": 2.303
  },
  {
    "text": "Alright, sit.",
    "start": 1435.44,
    "duration": 1.023
  },
  {
    "text": "Max you're such a good boy.",
    "start": 1438.465,
    "duration": 1.382
  },
  {
    "text": "All right here you go sweet girl.",
    "start": 1441.492,
    "duration": 3.321
  },
  {
    "text": "All right, my baby. Is that what you want?",
    "start": 1445.78,
    "duration": 3.4
  },
  {
    "text": "Is that what you want?",
    "start": 1449.18,
    "duration": 1.67
  },
  {
    "text": "Oh my goodness.",
    "start": 1453.47,
    "duration": 1.98
  },
  {
    "text": "I feel like if I have a treat,",
    "start": 1455.45,
    "duration": 2.0
  },
  {
    "text": "they have to have a treat too.",
    "start": 1457.45,
    "duration": 2.063
  }
]