[
  {
    "text": "Chef Buck here and today i'm going to blacken up\u00a0\na piece of fish so i'm going to take this lonely\u00a0\u00a0",
    "start": 0.08,
    "duration": 6.0
  },
  {
    "text": "little piece of fish and i'm going to blacken it\u00a0\nup easy peasy lemon squeezy when you're blackening\u00a0\u00a0",
    "start": 6.08,
    "duration": 5.52
  },
  {
    "text": "fish not a lot to it all you need is butter and\u00a0\ntoo much spice and a hot skillet i got a cast iron\u00a0\u00a0",
    "start": 11.6,
    "duration": 7.76
  },
  {
    "text": "skillet here so the first thing i'm going to do\u00a0\nis make sure that i'm turning on the right burner\u00a0\u00a0",
    "start": 19.36,
    "duration": 5.28
  },
  {
    "text": "then i'm going to put it on medium high heat and\u00a0\ngo ahead and start getting this skillet ready\u00a0\u00a0",
    "start": 24.64,
    "duration": 4.56
  },
  {
    "text": "because that's that's one of the most important\u00a0\nthings is making sure that when you're ready to\u00a0\u00a0",
    "start": 29.2,
    "duration": 4.8
  },
  {
    "text": "lay your fish in your skillet that your skillet\u00a0\nis super duper hot you know almost to the smoking\u00a0\u00a0",
    "start": 34.0,
    "duration": 5.84
  },
  {
    "text": "point now before i put my spice on my fish i'm\u00a0\ngoing to melt up this little piece of butter\u00a0\u00a0",
    "start": 39.84,
    "duration": 4.0
  },
  {
    "text": "so now i got my butter melted up now i'm going\u00a0\nto take my spice and this is a lot of spice\u00a0\u00a0",
    "start": 44.48,
    "duration": 4.32
  },
  {
    "text": "for one lonely little piece of fish but you want\u00a0\nto have too much spice but it doesn't have to be\u00a0\u00a0",
    "start": 48.8,
    "duration": 4.88
  },
  {
    "text": "overly spicy you don't have to use a lot of hot\u00a0\nspice you just want a lot of flavor to cook on the\u00a0\u00a0",
    "start": 53.68,
    "duration": 6.16
  },
  {
    "text": "outside of that fish i got a little chili powder\u00a0\na little onion powder garlic powder some paprika\u00a0\u00a0",
    "start": 59.84,
    "duration": 6.48
  },
  {
    "text": "some salt and pepper some italian seasonings you\u00a0\ncan use all of these spices you can use whatever\u00a0\u00a0",
    "start": 66.32,
    "duration": 5.04
  },
  {
    "text": "kind of mixture you like but just go heavy on\u00a0\nit so i'm going to throw all this in a bowl here\u00a0\u00a0",
    "start": 71.36,
    "duration": 6.0
  },
  {
    "text": "get my spices nice and mixed up\u00a0\u00a0",
    "start": 78.88,
    "duration": 1.92
  },
  {
    "text": "i'm going to take my fish coat it in my butter get\u00a0\nbutter all around on the outsides of my fish here\u00a0\u00a0",
    "start": 82.56,
    "duration": 6.72
  },
  {
    "text": "this fish was actually a frozen piece of fish i\u00a0\nmean if you can use fresh fish that's fantastic\u00a0\u00a0",
    "start": 89.28,
    "duration": 5.44
  },
  {
    "text": "but if you're using frozen fish you know make sure\u00a0\nit's completely thawed and that you've dried it\u00a0\u00a0",
    "start": 94.72,
    "duration": 6.32
  },
  {
    "text": "and then you can go ahead and let it\u00a0\nsit out and get to room temperature\u00a0\u00a0",
    "start": 101.76,
    "duration": 3.76
  },
  {
    "text": "so now we got it all slicked up with butter now\u00a0\ni'm going to take my seasoning and really give\u00a0\u00a0",
    "start": 107.12,
    "duration": 5.12
  },
  {
    "text": "one side of my fish a nice heavy coating of\u00a0\nspice and since this is a thick piece of fish\u00a0\u00a0",
    "start": 112.24,
    "duration": 6.72
  },
  {
    "text": "i'm going to go ahead and coat the sides as well\u00a0\u00a0",
    "start": 119.84,
    "duration": 2.0
  },
  {
    "text": "now we're just waiting for the skillet to heat up\u00a0\nokay i think my skillet is more than hot enough\u00a0\u00a0",
    "start": 123.12,
    "duration": 5.36
  },
  {
    "text": "so now i'll go ahead and lay my fish in the\u00a0\nskillet when it hits the pan it's going to sizzle",
    "start": 129.2,
    "duration": 4.24
  },
  {
    "text": "you want to make sure your fish starts to cook\u00a0\nright away now make sure and use up all of my\u00a0\u00a0",
    "start": 137.44,
    "duration": 5.44
  },
  {
    "text": "butter get this spice out of here now get my\u00a0\nremainder of spice and cover the uncoated side\u00a0\u00a0",
    "start": 142.88,
    "duration": 7.68
  },
  {
    "text": "really well and i know this seems like a lot of\u00a0\nspice but that's what blackened fish is now see\u00a0\u00a0",
    "start": 150.56,
    "duration": 6.24
  },
  {
    "text": "how smoky that is you know i really need to have\u00a0\nmy air vent on but that would muck up my audio so\u00a0\u00a0",
    "start": 156.8,
    "duration": 6.32
  },
  {
    "text": "i just gotta hope that i can cook this fish before\u00a0\nmy smoke alarm goes off and it doesn't take long\u00a0\u00a0",
    "start": 163.12,
    "duration": 6.24
  },
  {
    "text": "at all for fish to cook you know depending on\u00a0\nthe thickness of the fish you know just maybe\u00a0\u00a0",
    "start": 169.36,
    "duration": 4.88
  },
  {
    "text": "two or three minutes each side all right so\u00a0\nnow giving my fish a nice turn boom and look\u00a0\u00a0",
    "start": 174.24,
    "duration": 6.64
  },
  {
    "text": "at that nice black inside there now what's the\u00a0\ndifference between blackened fish and burnt fish\u00a0\u00a0",
    "start": 180.88,
    "duration": 7.12
  },
  {
    "text": "there's no difference i'm just over here burning\u00a0\nfish you know it's just the spice you know you're\u00a0\u00a0",
    "start": 189.76,
    "duration": 5.52
  },
  {
    "text": "just burning fish with spice on it now ideally\u00a0\nyou want to use a cast iron skillet for this\u00a0\u00a0",
    "start": 195.28,
    "duration": 6.72
  },
  {
    "text": "but if you don't have a cast iron skillet that's\u00a0\nfine you know i've blackened fish plenty of times\u00a0\u00a0",
    "start": 202.96,
    "duration": 4.4
  },
  {
    "text": "in just a regular non-stick pan you\u00a0\njust got to make sure that it's hot hot\u00a0\u00a0",
    "start": 207.92,
    "duration": 4.16
  },
  {
    "text": "hot hot since this fish is a little\u00a0\nthick and that looks perfect though",
    "start": 212.08,
    "duration": 4.56
  },
  {
    "text": "i'm gonna go ahead and cook the sides a\u00a0\nlittle bit get a nice sear on my edges",
    "start": 219.44,
    "duration": 6.4
  },
  {
    "text": "so there you have it a nice blackened piece\u00a0\nof fish with that nice charred spice on there\u00a0\u00a0",
    "start": 230.08,
    "duration": 6.08
  },
  {
    "text": "that charred butter and spice that's going\u00a0\nto be a delicious piece of blackened fish",
    "start": 236.16,
    "duration": 4.72
  },
  {
    "text": "looks like i need a little spot of color on there\u00a0\ncherry tomatoes are perfect for a quick makeover\u00a0\u00a0",
    "start": 243.12,
    "duration": 6.48
  },
  {
    "text": "but you always want to use an odd number you\u00a0\ndon't want to you don't want it to be even\u00a0\u00a0",
    "start": 250.88,
    "duration": 3.6
  },
  {
    "text": "you know you want to look dangerous\u00a0\nyou want it to be unpredictable",
    "start": 255.2,
    "duration": 2.64
  },
  {
    "text": "i think three tomatoes does that ready\u00a0\nin just a few minutes i don't know what\u00a0\u00a0",
    "start": 260.64,
    "duration": 5.76
  },
  {
    "text": "camera girl's eating today but\u00a0\ni'm pretty sure i got her beat",
    "start": 266.4,
    "duration": 3.68
  },
  {
    "text": "look how nice that is",
    "start": 277.44,
    "duration": 1.04
  },
  {
    "text": "life is hard without a camera\u00a0\ngirl i'll tell you that\u00a0\u00a0",
    "start": 281.28,
    "duration": 3.52
  },
  {
    "text": "cg has a lot of qualities so many good ones\u00a0\nbut about her eighth or ninth best quality\u00a0\u00a0",
    "start": 286.48,
    "duration": 6.32
  },
  {
    "text": "is being the camera girl you\u00a0\njust can't have too much spice",
    "start": 293.76,
    "duration": 3.6
  },
  {
    "text": "if you want to check out the recipe i'll\u00a0\nbe written down below you can head over to\u00a0\u00a0",
    "start": 302.48,
    "duration": 2.64
  },
  {
    "text": "MyFoodChannel.com check out all our recipes over\u00a0\nthere thanks for watching and doing all that stuff\u00a0\u00a0",
    "start": 305.12,
    "duration": 5.6
  },
  {
    "text": "and i'll see you next weekend hopefully\u00a0\ncamera girl be here but either which way\u00a0\u00a0",
    "start": 311.52,
    "duration": 4.4
  },
  {
    "text": "either i'll be eating with her i'll be eating\u00a0\nall on my lonesome we'll see you then bye-bye",
    "start": 316.88,
    "duration": 5.52
  }
]